Workbook
Name Slicer_Category: #N/A
Name Slicer_Order_Status: #N/A
Name Slicer_Region: #N/A

Sheet Raw_Data
A1: Order_ID | B1: Order_Date | C1: Customer_ID | D1: Customer_Name | E1: Product_ID | F1: Product | G1: Category | H1: Sub_Category | I1: Region | J1: State | K1: Sales | L1: Cost | M1: Quantity | N1: Discount | O1: Payment_Mode | P1: Order_Status
A2: ORD0001 | B2: 45573 | C2: C021 | D2: Akash Chauhan | E2: P004 | F2: Smart Watch | G2: Electronics | H2: Wearables | I2: North | J2: Delhi | K2: 12021.92 | L2: 5667.86 | M2: 2 | N2: 0.2 | O2: UPI | P2: Cancelled
A3: ORD0002 | B3: 45515 | C3: C002 | D3: Priya Singh | E3: P001 | F3: Laptop | G3: Electronics | H3: Computers | I3: North | J3: Uttar Pradesh | K3: 102710.69 | L3: 96102.82 | M3: 2 | N3: 0.05 | O3: Cash on Delivery | P3: Cancelled
A4: ORD0003 | B4: 45576 | C4: C008 | D4: Anjali Patel | E4: P015 | F4: Jeans | G4: Fashion | H4: Clothing | I4: East | J4: West Bengal | K4: 727.13 | L4: 525.88 | M4: 1 | N4: 0.15 | O4: Debit Card | P4: Shipped
A5: ORD0004 | B5: 45636 | C5: C005 | D5: Simran Kaur | E5: P007 | F5: Study Table | G5: Furniture | H5: Tables | I5: Central | J5: Madhya Pradesh | K5: 7940.38 | L5: 6429.84 | M5: 1 | N5: 0.1 | O5: Cash on Delivery | P5: Shipped
A6: ORD0005 | B6: 45419 | C6: C002 | D6: Priya Singh | E6: P015 | F6: Jeans | G6: Fashion | H6: Clothing | I6: West | J6: Rajasthan | K6: 3421.09 | L6: 1831.52 | M6: 4 | N6: 0.2 | O6: Debit Card | P6: Delivered
A7: ORD0006 | B7: 45969 | C7: C023 | D7: Varun Kapoor | E7: P003 | F7: Headphones | G7: Electronics | H7: Accessories | I7: North | J7: Delhi | K7: 12224.09 | L7: 3796.6 | M7: 2 | N7: 0.05 | O7: UPI | P7: Cancelled
A8: ORD0007 | B8: 45665 | C8: C009 | D8: Arjun Rao | E8: P015 | F8: Jeans | G8: Fashion | H8: Clothing | I8: East | J8: Odisha | K8: 1683.38 | L8: 974.04 | M8: 2 | N8: 0.1 | O8: UPI | P8: Delivered
A9: ORD0008 | B9: 45765 | C9: C018 | D9: Divya Shah | E9: P008 | F9: Bookshelf | G9: Furniture | H9: Storage | I9: North | J9: Punjab | K9: 30682.11 | L9: 15263.84 | M9: 4 | N9: 0.2 | O9: Credit Card | P9: Processing
A10: ORD0009 | B10: 45324 | C10: C025 | D10: Deepak Soni | E10: P002 | F10: Mobile | G10: Electronics | H10: Phones | I10: South | J10: Karnataka | K10: 50741.38 | L10: 52932.57 | M10: 3 | N10: 0.2 | O10: Debit Card | P10: Delivered
A11: ORD0010 | B11: 45950 | C11: C021 | D11: Akash Chauhan | E11: P016 | F11: Mixer Grinder | G11: Home Appliances | H11: Kitchen | I11: West | J11: Maharashtra | K11: 8007.9 | L11: 6685.72 | M11: 4 | N11: 0.2 | O11: Cash on Delivery | P11: Shipped
A12: ORD0011 | B12: 45889 | C12: C024 | D12: Nisha Agarwal | E12: P019 | F12: Vacuum Cleaner | G12: Home Appliances | H12: Cleaning | I12: West | J12: Maharashtra | K12: 34148.36 | L12: 13613.6 | M12: 4 | N12: 0.05 | O12: Cash on Delivery | P12: Returned
A13: ORD0012 | B13: 45404 | C13: C003 | D13: Amit Kumar | E13: P002 | F13: Mobile | G13: Electronics | H13: Phones | I13: Central | J13: Chhattisgarh | K13: 54254.58 | L13: 36917.62 | M13: 2 | N13: 0.15 | O13: Cash on Delivery | P13: Delivered
... A1001: ORD1000 | B1001: 45682 | C1001: C021 | D1001: Akash Chauhan | E1001: P011 | F1001: Running Shoes | G1001: Fashion | H1001: Footwear | I1001: West | J1001: Maharashtra | K1001: 13972.27 | L1001: 6559.5 | M1001: 5 | N1001: 0.05 | O1001: Credit Card | P1001: Shipped

Sheet Cleaned_Data
A1: Order_ID | B1: Order_Date | C1: Customer_ID | D1: Customer_Name | E1: Product_ID | F1: Product | G1: Category | H1: Sub_Category | I1: Region | J1: State | K1: Sales | L1: Cost | M1: Quantity | N1: Discount | O1: Payment_Mode | P1: Order_Status | Q1: Clean_Customer_Name | R1: Profit | S1: Profit_Margin | T1: Year | U1: Month | V1: Quarter | W1: Sales_Category | X1: Profit_Status | Y1: Large_Order | Z1: Upper_Name | AA1: Lower_Name | AB1: Name_Length | AC1: Order_Prefix | AD1: Order_Number | AE1: Customer_Region | AF1: MID | AG1: Product_Manager | AH1: Manager_VLOOKUP | AI1: Manager_INDEXMATCH
A2: ORD0683 | B2: 45335 | C2: C011 | D2: Vikas Yadav | E2: P002 | F2: Mobile | G2: Electronics | H2: Phones | I2: South | J2: Telangana | K2: 102839.74 | L2: 66501.88 | M2: 4 | N2: 0.2 | O2: Net Banking | P2: Delivered | Q2: =TRIM(SalesData[[#This Row],[Customer_Name]]) -> Vikas Yadav | R2: =SalesData[[#This Row],[Sales]]-SalesData[[#This Row],[Cost]] -> 36337.86 | S2: =IFERROR(SalesData[[#This Row],[Profit]]/SalesData[[#This Row],[Sales]],0) -> 0.35334453 | T2: =YEAR(SalesData[[#This Row],[Order_Date]]) -> 2024 | U2: =TEXT(SalesData[[#This Row],[Order_Date]],"mmm") -> Feb | V2: ="Q"&ROUNDUP(MONTH(SalesData[[#This Row],[Order_Date]])/3,0) -> Q1 | W2: =IF(SalesData[[#This Row],[Sales]]>=50000,"High",IF(AND(SalesData[[#This Row],[Sales]]>= 20000, SalesData[[#This Row],[Sales]]< 50000),"Medium","Low")) -> High | X2: =IF(SalesData[[#This Row],[Profit]]>0,"Profit","Loss") -> Profit | Y2: =IF(AND(SalesData[[#This Row],[Sales]]>= 50000, SalesData[[#This Row],[Quantity]]>=2),"Yes","No") -> Yes | Z2: =UPPER(SalesData[[#This Row],[Customer_Name]]) -> VIKAS YADAV | AA2: =LOWER(SalesData[[#This Row],[Customer_Name]]) -> vikas yadav | AB2: =LEN(SalesData[[#This Row],[Customer_Name]]) -> 11 | AC2: =LEFT(SalesData[[#This Row],[Order_ID]],3) -> ORD | AD2: =RIGHT(SalesData[[#This Row],[Order_ID]],4) -> 0683 | AE2: =_xlfn.CONCAT(SalesData[[#This Row],[Clean_Customer_Name]],"-",SalesData[[#This Row],[Region]]) -> Vikas Yadav-South | AF2: =MID(SalesData[[#This Row],[Order_ID]],4,4) -> 0683 | AG2: =_xlfn.SINGLE(_xlfn.XLOOKUP(SalesData[[#This Row],[Product]],Product_Master!A:A,Product_Master!B:B,"Not Found")) -> Priya | AH2: =VLOOKUP(SalesData[[#This Row],[Product]],Product_Master!$A$1:$B$21,2,FALSE) -> Priya
A3: ORD0337 | B3: 45759 | C3: C011 | D3: Vikas Yadav | E3: P003 | F3: Headphones | G3: Electronics | H3: Accessories | I3: West | J3: Rajasthan | K3: 2991.16 | L3: 1752.81 | M3: 1 | N3: 0.1 | O3: Cash on Delivery | P3: Delivered | Q3: =TRIM(SalesData[[#This Row],[Customer_Name]]) -> Vikas Yadav | R3: =SalesData[[#This Row],[Sales]]-SalesData[[#This Row],[Cost]] -> 1238.35 | S3: =IFERROR(SalesData[[#This Row],[Profit]]/SalesData[[#This Row],[Sales]],0) -> 0.41400326 | T3: =YEAR(SalesData[[#This Row],[Order_Date]]) -> 2025 | U3: =TEXT(SalesData[[#This Row],[Order_Date]],"mmm") -> Apr | V3: ="Q"&ROUNDUP(MONTH(SalesData[[#This Row],[Order_Date]])/3,0) -> Q2 | W3: =IF(SalesData[[#This Row],[Sales]]>=50000,"High",IF(AND(SalesData[[#This Row],[Sales]]>= 20000, SalesData[[#This Row],[Sales]]< 50000),"Medium","Low")) -> Low | X3: =IF(SalesData[[#This Row],[Profit]]>0,"Profit","Loss") -> Profit | Y3: =IF(AND(SalesData[[#This Row],[Sales]]>= 50000, SalesData[[#This Row],[Quantity]]>=2),"Yes","No") -> No | Z3: =UPPER(SalesData[[#This Row],[Customer_Name]]) -> VIKAS YADAV | AA3: =LOWER(SalesData[[#This Row],[Customer_Name]]) -> vikas yadav | AB3: =LEN(SalesData[[#This Row],[Customer_Name]]) -> 11 | AC3: =LEFT(SalesData[[#This Row],[Order_ID]],3) -> ORD | AD3: =RIGHT(SalesData[[#This Row],[Order_ID]],4) -> 0337 | AE3: =_xlfn.CONCAT(SalesData[[#This Row],[Clean_Customer_Name]],"-",SalesData[[#This Row],[Region]]) -> Vikas Yadav-West | AF3: =MID(SalesData[[#This Row],[Order_ID]],4,4) -> 0337 | AG3: =_xlfn.SINGLE(_xlfn.XLOOKUP(SalesData[[#This Row],[Product]],Product_Master!A:A,Product_Master!B:B,"Not Found")) -> #NAME? | AH3: =VLOOKUP(SalesData[[#This Row],[Product]],Product_Master!$A$1:$B$21,2,FALSE) -> Amit
A4: ORD0591 | B4: 45837 | C4: C011 | D4: Vikas Yadav | E4: P003 | F4: Headphones | G4: Electronics | H4: Accessories | I4: West | J4: Rajasthan | K4: 5491.4 | L4: 1686.29 | M4: 1 | N4: 0.05 | O4: UPI | P4: Processing | Q4: =TRIM(SalesData[[#This Row],[Customer_Name]]) -> Vikas Yadav | R4: =SalesData[[#This Row],[Sales]]-SalesData[[#This Row],[Cost]] -> 3805.11 | S4: =IFERROR(SalesData[[#This Row],[Profit]]/SalesData[[#This Row],[Sales]],0) -> 0.69292166 | T4: =YEAR(SalesData[[#This Row],[Order_Date]]) -> 2025 | U4: =TEXT(SalesData[[#This Row],[Order_Date]],"mmm") -> Jun | V4: ="Q"&ROUNDUP(MONTH(SalesData[[#This Row],[Order_Date]])/3,0) -> Q2 | W4: =IF(SalesData[[#This Row],[Sales]]>=50000,"High",IF(AND(SalesData[[#This Row],[Sales]]>= 20000, SalesData[[#This Row],[Sales]]< 50000),"Medium","Low")) -> Low | X4: =IF(SalesData[[#This Row],[Profit]]>0,"Profit","Loss") -> Profit | Y4: =IF(AND(SalesData[[#This Row],[Sales]]>= 50000, SalesData[[#This Row],[Quantity]]>=2),"Yes","No") -> No | Z4: =UPPER(SalesData[[#This Row],[Customer_Name]]) -> VIKAS YADAV | AA4: =LOWER(SalesData[[#This Row],[Customer_Name]]) -> vikas yadav | AB4: =LEN(SalesData[[#This Row],[Customer_Name]]) -> 11 | AC4: =LEFT(SalesData[[#This Row],[Order_ID]],3) -> ORD | AD4: =RIGHT(SalesData[[#This Row],[Order_ID]],4) -> 0591 | AE4: =_xlfn.CONCAT(SalesData[[#This Row],[Clean_Customer_Name]],"-",SalesData[[#This Row],[Region]]) -> Vikas Yadav-West | AF4: =MID(SalesData[[#This Row],[Order_ID]],4,4) -> 0591 | AG4: =_xlfn.SINGLE(_xlfn.XLOOKUP(SalesData[[#This Row],[Product]],Product_Master!A:A,Product_Master!B:B,"Not Found")) -> #NAME? | AH4: =VLOOKUP(SalesData[[#This Row],[Product]],Product_Master!$A$1:$B$21,2,FALSE) -> Amit
A5: ORD0781 | B5: 45500 | C5: C011 | D5: Vikas Yadav | E5: P003 | F5: Headphones | G5: Electronics | H5: Accessories | I5: East | J5: Odisha | K5: 12551.82 | L5: 6864.4 | M5: 4 | N5: 0.05 | O5: Debit Card | P5: Delivered | Q5: =TRIM(SalesData[[#This Row],[Customer_Name]]) -> Vikas Yadav | R5: =SalesData[[#This Row],[Sales]]-SalesData[[#This Row],[Cost]] -> 5687.42 | S5: =IFERROR(SalesData[[#This Row],[Profit]]/SalesData[[#This Row],[Sales]],0) -> 0.45311517 | T5: =YEAR(SalesData[[#This Row],[Order_Date]]) -> 2024 | U5: =TEXT(SalesData[[#This Row],[Order_Date]],"mmm") -> Jul | V5: ="Q"&ROUNDUP(MONTH(SalesData[[#This Row],[Order_Date]])/3,0) -> Q3 | W5: =IF(SalesData[[#This Row],[Sales]]>=50000,"High",IF(AND(SalesData[[#This Row],[Sales]]>= 20000, SalesData[[#This Row],[Sales]]< 50000),"Medium","Low")) -> Low | X5: =IF(SalesData[[#This Row],[Profit]]>0,"Profit","Loss") -> Profit | Y5: =IF(AND(SalesData[[#This Row],[Sales]]>= 50000, SalesData[[#This Row],[Quantity]]>=2),"Yes","No") -> No | Z5: =UPPER(SalesData[[#This Row],[Customer_Name]]) -> VIKAS YADAV | AA5: =LOWER(SalesData[[#This Row],[Customer_Name]]) -> vikas yadav | AB5: =LEN(SalesData[[#This Row],[Customer_Name]]) -> 11 | AC5: =LEFT(SalesData[[#This Row],[Order_ID]],3) -> ORD | AD5: =RIGHT(SalesData[[#This Row],[Order_ID]],4) -> 0781 | AE5: =_xlfn.CONCAT(SalesData[[#This Row],[Clean_Customer_Name]],"-",SalesData[[#This Row],[Region]]) -> Vikas Yadav-East | AF5: =MID(SalesData[[#This Row],[Order_ID]],4,4) -> 0781 | AG5: =_xlfn.SINGLE(_xlfn.XLOOKUP(SalesData[[#This Row],[Product]],Product_Master!A:A,Product_Master!B:B,"Not Found")) -> #NAME? | AH5: =VLOOKUP(SalesData[[#This Row],[Product]],Product_Master!$A$1:$B$21,2,FALSE) -> Amit
A6: ORD0933 | B6: 45484 | C6: C011 | D6: Vikas Yadav | E6: P003 | F6: Headphones | G6: Electronics | H6: Accessories | I6: South | J6: Telangana | K6: 19553.17 | L6: 7589 | M6: 4 | N6: 0.05 | O6: Net Banking | P6: Returned | Q6: =TRIM(SalesData[[#This Row],[Customer_Name]]) -> Vikas Yadav | R6: =SalesData[[#This Row],[Sales]]-SalesData[[#This Row],[Cost]] -> 11964.17 | S6: =IFERROR(SalesData[[#This Row],[Profit]]/SalesData[[#This Row],[Sales]],0) -> 0.61187879 | T6: =YEAR(SalesData[[#This Row],[Order_Date]]) -> 2024 | U6: =TEXT(SalesData[[#This Row],[Order_Date]],"mmm") -> Jul | V6: ="Q"&ROUNDUP(MONTH(SalesData[[#This Row],[Order_Date]])/3,0) -> Q3 | W6: =IF(SalesData[[#This Row],[Sales]]>=50000,"High",IF(AND(SalesData[[#This Row],[Sales]]>= 20000, SalesData[[#This Row],[Sales]]< 50000),"Medium","Low")) -> Low | X6: =IF(SalesData[[#This Row],[Profit]]>0,"Profit","Loss") -> Profit | Y6: =IF(AND(SalesData[[#This Row],[Sales]]>= 50000, SalesData[[#This Row],[Quantity]]>=2),"Yes","No") -> No | Z6: =UPPER(SalesData[[#This Row],[Customer_Name]]) -> VIKAS YADAV | AA6: =LOWER(SalesData[[#This Row],[Customer_Name]]) -> vikas yadav | AB6: =LEN(SalesData[[#This Row],[Customer_Name]]) -> 11 | AC6: =LEFT(SalesData[[#This Row],[Order_ID]],3) -> ORD | AD6: =RIGHT(SalesData[[#This Row],[Order_ID]],4) -> 0933 | AE6: =_xlfn.CONCAT(SalesData[[#This Row],[Clean_Customer_Name]],"-",SalesData[[#This Row],[Region]]) -> Vikas Yadav-South | AF6: =MID(SalesData[[#This Row],[Order_ID]],4,4) -> 0933 | AG6: =_xlfn.SINGLE(_xlfn.XLOOKUP(SalesData[[#This Row],[Product]],Product_Master!A:A,Product_Master!B:B,"Not Found")) -> #NAME? | AH6: =VLOOKUP(SalesData[[#This Row],[Product]],Product_Master!$A$1:$B$21,2,FALSE) -> Amit | AJ6: Metric | AK6: Result
A7: ORD0081 | B7: 45550 | C7: C011 | D7: Vikas Yadav | E7: P006 | F7: Office Chair | G7: Furniture | H7: Chairs | I7: North | J7: Delhi | K7: 18460.13 | L7: 16610.72 | M7: 4 | N7: 0.15 | O7: UPI | P7: Delivered | Q7: =TRIM(SalesData[[#This Row],[Customer_Name]]) -> Vikas Yadav | R7: =SalesData[[#This Row],[Sales]]-SalesData[[#This Row],[Cost]] -> 1849.41 | S7: =IFERROR(SalesData[[#This Row],[Profit]]/SalesData[[#This Row],[Sales]],0) -> 0.10018402 | T7: =YEAR(SalesData[[#This Row],[Order_Date]]) -> 2024 | U7: =TEXT(SalesData[[#This Row],[Order_Date]],"mmm") -> Sept | V7: ="Q"&ROUNDUP(MONTH(SalesData[[#This Row],[Order_Date]])/3,0) -> Q3 | W7: =IF(SalesData[[#This Row],[Sales]]>=50000,"High",IF(AND(SalesData[[#This Row],[Sales]]>= 20000, SalesData[[#This Row],[Sales]]< 50000),"Medium","Low")) -> Low | X7: =IF(SalesData[[#This Row],[Profit]]>0,"Profit","Loss") -> Profit | Y7: =IF(AND(SalesData[[#This Row],[Sales]]>= 50000, SalesData[[#This Row],[Quantity]]>=2),"Yes","No") -> No | Z7: =UPPER(SalesData[[#This Row],[Customer_Name]]) -> VIKAS YADAV | AA7: =LOWER(SalesData[[#This Row],[Customer_Name]]) -> vikas yadav | AB7: =LEN(SalesData[[#This Row],[Customer_Name]]) -> 11 | AC7: =LEFT(SalesData[[#This Row],[Order_ID]],3) -> ORD | AD7: =RIGHT(SalesData[[#This Row],[Order_ID]],4) -> 0081 | AE7: =_xlfn.CONCAT(SalesData[[#This Row],[Clean_Customer_Name]],"-",SalesData[[#This Row],[Region]]) -> Vikas Yadav-North | AF7: =MID(SalesData[[#This Row],[Order_ID]],4,4) -> 0081 | AG7: =_xlfn.SINGLE(_xlfn.XLOOKUP(SalesData[[#This Row],[Product]],Product_Master!A:A,Product_Master!B:B,"Not Found")) -> #NAME? | AH7: =VLOOKUP(SalesData[[#This Row],[Product]],Product_Master!$A$1:$B$21,2,FALSE) -> Karan | AJ7: High Sales Orders | AK7: =COUNTIF(SalesData[Sales_Category],"High") -> 167
A8: ORD0149 | B8: 45814 | C8: C011 | D8: Vikas Yadav | E8: P006 | F8: Office Chair | G8: Furniture | H8: Chairs | I8: North | J8: Uttar Pradesh | K8: 5576.1 | L8: 4527.54 | M8: 1 | N8: 0.1 | O8: Debit Card | P8: Delivered | Q8: =TRIM(SalesData[[#This Row],[Customer_Name]]) -> Vikas Yadav | R8: =SalesData[[#This Row],[Sales]]-SalesData[[#This Row],[Cost]] -> 1048.56 | S8: =IFERROR(SalesData[[#This Row],[Profit]]/SalesData[[#This Row],[Sales]],0) -> 0.18804541 | T8: =YEAR(SalesData[[#This Row],[Order_Date]]) -> 2025 | U8: =TEXT(SalesData[[#This Row],[Order_Date]],"mmm") -> Jun | V8: ="Q"&ROUNDUP(MONTH(SalesData[[#This Row],[Order_Date]])/3,0) -> Q2 | W8: =IF(SalesData[[#This Row],[Sales]]>=50000,"High",IF(AND(SalesData[[#This Row],[Sales]]>= 20000, SalesData[[#This Row],[Sales]]< 50000),"Medium","Low")) -> Low | X8: =IF(SalesData[[#This Row],[Profit]]>0,"Profit","Loss") -> Profit | Y8: =IF(AND(SalesData[[#This Row],[Sales]]>= 50000, SalesData[[#This Row],[Quantity]]>=2),"Yes","No") -> No | Z8: =UPPER(SalesData[[#This Row],[Customer_Name]]) -> VIKAS YADAV | AA8: =LOWER(SalesData[[#This Row],[Customer_Name]]) -> vikas yadav | AB8: =LEN(SalesData[[#This Row],[Customer_Name]]) -> 11 | AC8: =LEFT(SalesData[[#This Row],[Order_ID]],3) -> ORD | AD8: =RIGHT(SalesData[[#This Row],[Order_ID]],4) -> 0149 | AE8: =_xlfn.CONCAT(SalesData[[#This Row],[Clean_Customer_Name]],"-",SalesData[[#This Row],[Region]]) -> Vikas Yadav-North | AF8: =MID(SalesData[[#This Row],[Order_ID]],4,4) -> 0149 | AG8: =_xlfn.SINGLE(_xlfn.XLOOKUP(SalesData[[#This Row],[Product]],Product_Master!A:A,Product_Master!B:B,"Not Found")) -> #NAME? | AH8: =VLOOKUP(SalesData[[#This Row],[Product]],Product_Master!$A$1:$B$21,2,FALSE) -> Karan
A9: ORD0688 | B9: 45338 | C9: C011 | D9: Vikas Yadav | E9: P007 | F9: Study Table | G9: Furniture | H9: Tables | I9: Central | J9: Madhya Pradesh | K9: 38170.49 | L9: 32714.15 | M9: 5 | N9: 0.1 | O9: Credit Card | P9: Cancelled | Q9: =TRIM(SalesData[[#This Row],[Customer_Name]]) -> Vikas Yadav | R9: =SalesData[[#This Row],[Sales]]-SalesData[[#This Row],[Cost]] -> 5456.34 | S9: =IFERROR(SalesData[[#This Row],[Profit]]/SalesData[[#This Row],[Sales]],0) -> 0.14294655 | T9: =YEAR(SalesData[[#This Row],[Order_Date]]) -> 2024 | U9: =TEXT(SalesData[[#This Row],[Order_Date]],"mmm") -> Feb | V9: ="Q"&ROUNDUP(MONTH(SalesData[[#This Row],[Order_Date]])/3,0) -> Q1 | W9: =IF(SalesData[[#This Row],[Sales]]>=50000,"High",IF(AND(SalesData[[#This Row],[Sales]]>= 20000, SalesData[[#This Row],[Sales]]< 50000),"Medium","Low")) -> Medium | X9: =IF(SalesData[[#This Row],[Profit]]>0,"Profit","Loss") -> Profit | Y9: =IF(AND(SalesData[[#This Row],[Sales]]>= 50000, SalesData[[#This Row],[Quantity]]>=2),"Yes","No") -> No | Z9: =UPPER(SalesData[[#This Row],[Customer_Name]]) -> VIKAS YADAV | AA9: =LOWER(SalesData[[#This Row],[Customer_Name]]) -> vikas yadav | AB9: =LEN(SalesData[[#This Row],[Customer_Name]]) -> 11 | AC9: =LEFT(SalesData[[#This Row],[Order_ID]],3) -> ORD | AD9: =RIGHT(SalesData[[#This Row],[Order_ID]],4) -> 0688 | AE9: =_xlfn.CONCAT(SalesData[[#This Row],[Clean_Customer_Name]],"-",SalesData[[#This Row],[Region]]) -> Vikas Yadav-Central | AF9: =MID(SalesData[[#This Row],[Order_ID]],4,4) -> 0688 | AG9: =_xlfn.SINGLE(_xlfn.XLOOKUP(SalesData[[#This Row],[Product]],Product_Master!A:A,Product_Master!B:B,"Not Found")) -> #NAME? | AH9: =VLOOKUP(SalesData[[#This Row],[Product]],Product_Master!$A$1:$B$21,2,FALSE) -> Rohan | AJ9: High Sales from Region | AK9: =COUNTIFS(SalesData[Sales_Category],"High",SalesData[Region],"North") -> 33
A10: ORD0911 | B10: 45779 | C10: C011 | D10: Vikas Yadav | E10: P007 | F10: Study Table | G10: Furniture | H10: Tables | I10: East | J10: Odisha | K10: 35854.21 | L10: 28558.68 | M10: 4 | N10: 0.2 | O10: Cash on Delivery | P10: Processing | Q10: =TRIM(SalesData[[#This Row],[Customer_Name]]) -> Vikas Yadav | R10: =SalesData[[#This Row],[Sales]]-SalesData[[#This Row],[Cost]] -> 7295.53 | S10: =IFERROR(SalesData[[#This Row],[Profit]]/SalesData[[#This Row],[Sales]],0) -> 0.20347764 | T10: =YEAR(SalesData[[#This Row],[Order_Date]]) -> 2025 | U10: =TEXT(SalesData[[#This Row],[Order_Date]],"mmm") -> May | V10: ="Q"&ROUNDUP(MONTH(SalesData[[#This Row],[Order_Date]])/3,0) -> Q2 | W10: =IF(SalesData[[#This Row],[Sales]]>=50000,"High",IF(AND(SalesData[[#This Row],[Sales]]>= 20000, SalesData[[#This Row],[Sales]]< 50000),"Medium","Low")) -> Medium | X10: =IF(SalesData[[#This Row],[Profit]]>0,"Profit","Loss") -> Profit | Y10: =IF(AND(SalesData[[#This Row],[Sales]]>= 50000, SalesData[[#This Row],[Quantity]]>=2),"Yes","No") -> No | Z10: =UPPER(SalesData[[#This Row],[Customer_Name]]) -> VIKAS YADAV | AA10: =LOWER(SalesData[[#This Row],[Customer_Name]]) -> vikas yadav | AB10: =LEN(SalesData[[#This Row],[Customer_Name]]) -> 11 | AC10: =LEFT(SalesData[[#This Row],[Order_ID]],3) -> ORD | AD10: =RIGHT(SalesData[[#This Row],[Order_ID]],4) -> 0911 | AE10: =_xlfn.CONCAT(SalesData[[#This Row],[Clean_Customer_Name]],"-",SalesData[[#This Row],[Region]]) -> Vikas Yadav-East | AF10: =MID(SalesData[[#This Row],[Order_ID]],4,4) -> 0911 | AG10: =_xlfn.SINGLE(_xlfn.XLOOKUP(SalesData[[#This Row],[Product]],Product_Master!A:A,Product_Master!B:B,"Not Found")) -> #NAME? | AH10: =VLOOKUP(SalesData[[#This Row],[Product]],Product_Master!$A$1:$B$21,2,FALSE) -> Rohan
A11: ORD0124 | B11: 45870 | C11: C011 | D11: Vikas Yadav | E11: P008 | F11: Bookshelf | G11: Furniture | H11: Storage | I11: North | J11: Punjab | K11: 16536.97 | L11: 7309.78 | M11: 2 | N11: 0.05 | O11: Cash on Delivery | P11: Delivered | Q11: =TRIM(SalesData[[#This Row],[Customer_Name]]) -> Vikas Yadav | R11: =SalesData[[#This Row],[Sales]]-SalesData[[#This Row],[Cost]] -> 9227.19 | S11: =IFERROR(SalesData[[#This Row],[Profit]]/SalesData[[#This Row],[Sales]],0) -> 0.55797344 | T11: =YEAR(SalesData[[#This Row],[Order_Date]]) -> 2025 | U11: =TEXT(SalesData[[#This Row],[Order_Date]],"mmm") -> Aug | V11: ="Q"&ROUNDUP(MONTH(SalesData[[#This Row],[Order_Date]])/3,0) -> Q3 | W11: =IF(SalesData[[#This Row],[Sales]]>=50000,"High",IF(AND(SalesData[[#This Row],[Sales]]>= 20000, SalesData[[#This Row],[Sales]]< 50000),"Medium","Low")) -> Low | X11: =IF(SalesData[[#This Row],[Profit]]>0,"Profit","Loss") -> Profit | Y11: =IF(AND(SalesData[[#This Row],[Sales]]>= 50000, SalesData[[#This Row],[Quantity]]>=2),"Yes","No") -> No | Z11: =UPPER(SalesData[[#This Row],[Customer_Name]]) -> VIKAS YADAV | AA11: =LOWER(SalesData[[#This Row],[Customer_Name]]) -> vikas yadav | AB11: =LEN(SalesData[[#This Row],[Customer_Name]]) -> 11 | AC11: =LEFT(SalesData[[#This Row],[Order_ID]],3) -> ORD | AD11: =RIGHT(SalesData[[#This Row],[Order_ID]],4) -> 0124 | AE11: =_xlfn.CONCAT(SalesData[[#This Row],[Clean_Customer_Name]],"-",SalesData[[#This Row],[Region]]) -> Vikas Yadav-North | AF11: =MID(SalesData[[#This Row],[Order_ID]],4,4) -> 0124 | AG11: =_xlfn.SINGLE(_xlfn.XLOOKUP(SalesData[[#This Row],[Product]],Product_Master!A:A,Product_Master!B:B,"Not Found")) -> #NAME? | AH11: =VLOOKUP(SalesData[[#This Row],[Product]],Product_Master!$A$1:$B$21,2,FALSE) -> Anjali | AJ11: Total Sales from North | AK11: =SUMIF(SalesData[Region],"North",SalesData[Sales]) -> 5874947
A12: ORD0699 | B12: 45534 | C12: C011 | D12: Vikas Yadav | E12: P008 | F12: Bookshelf | G12: Furniture | H12: Storage | I12: North | J12: Uttar Pradesh | K12: 24901.17 | L12: 17183.64 | M12: 4 | N12: 0.05 | O12: UPI | P12: Returned | Q12: =TRIM(SalesData[[#This Row],[Customer_Name]]) -> Vikas Yadav | R12: =SalesData[[#This Row],[Sales]]-SalesData[[#This Row],[Cost]] -> 7717.53 | S12: =IFERROR(SalesData[[#This Row],[Profit]]/SalesData[[#This Row],[Sales]],0) -> 0.3099264 | T12: =YEAR(SalesData[[#This Row],[Order_Date]]) -> 2024 | U12: =TEXT(SalesData[[#This Row],[Order_Date]],"mmm") -> Aug | V12: ="Q"&ROUNDUP(MONTH(SalesData[[#This Row],[Order_Date]])/3,0) -> Q3 | W12: =IF(SalesData[[#This Row],[Sales]]>=50000,"High",IF(AND(SalesData[[#This Row],[Sales]]>= 20000, SalesData[[#This Row],[Sales]]< 50000),"Medium","Low")) -> Medium | X12: =IF(SalesData[[#This Row],[Profit]]>0,"Profit","Loss") -> Profit | Y12: =IF(AND(SalesData[[#This Row],[Sales]]>= 50000, SalesData[[#This Row],[Quantity]]>=2),"Yes","No") -> No | Z12: =UPPER(SalesData[[#This Row],[Customer_Name]]) -> VIKAS YADAV | AA12: =LOWER(SalesData[[#This Row],[Customer_Name]]) -> vikas yadav | AB12: =LEN(SalesData[[#This Row],[Customer_Name]]) -> 11 | AC12: =LEFT(SalesData[[#This Row],[Order_ID]],3) -> ORD | AD12: =RIGHT(SalesData[[#This Row],[Order_ID]],4) -> 0699 | AE12: =_xlfn.CONCAT(SalesData[[#This Row],[Clean_Customer_Name]],"-",SalesData[[#This Row],[Region]]) -> Vikas Yadav-North | AF12: =MID(SalesData[[#This Row],[Order_ID]],4,4) -> 0699 | AG12: =_xlfn.SINGLE(_xlfn.XLOOKUP(SalesData[[#This Row],[Product]],Product_Master!A:A,Product_Master!B:B,"Not Found")) -> #NAME? | AH12: =VLOOKUP(SalesData[[#This Row],[Product]],Product_Master!$A$1:$B$21,2,FALSE) -> Anjali
A13: ORD0935 | B13: 45727 | C13: C011 | D13: Vikas Yadav | E13: P008 | F13: Bookshelf | G13: Furniture | H13: Storage | I13: West | J13: Maharashtra | K13: 29849.98 | L13: 16841.08 | M13: 4 | N13: 0.1 | O13: Debit Card | P13: Delivered | Q13: =TRIM(SalesData[[#This Row],[Customer_Name]]) -> Vikas Yadav | R13: =SalesData[[#This Row],[Sales]]-SalesData[[#This Row],[Cost]] -> 13008.9 | S13: =IFERROR(SalesData[[#This Row],[Profit]]/SalesData[[#This Row],[Sales]],0) -> 0.43580934 | T13: =YEAR(SalesData[[#This Row],[Order_Date]]) -> 2025 | U13: =TEXT(SalesData[[#This Row],[Order_Date]],"mmm") -> Mar | V13: ="Q"&ROUNDUP(MONTH(SalesData[[#This Row],[Order_Date]])/3,0) -> Q1 | W13: =IF(SalesData[[#This Row],[Sales]]>=50000,"High",IF(AND(SalesData[[#This Row],[Sales]]>= 20000, SalesData[[#This Row],[Sales]]< 50000),"Medium","Low")) -> Medium | X13: =IF(SalesData[[#This Row],[Profit]]>0,"Profit","Loss") -> Profit | Y13: =IF(AND(SalesData[[#This Row],[Sales]]>= 50000, SalesData[[#This Row],[Quantity]]>=2),"Yes","No") -> No | Z13: =UPPER(SalesData[[#This Row],[Customer_Name]]) -> VIKAS YADAV | AA13: =LOWER(SalesData[[#This Row],[Customer_Name]]) -> vikas yadav | AB13: =LEN(SalesData[[#This Row],[Customer_Name]]) -> 11 | AC13: =LEFT(SalesData[[#This Row],[Order_ID]],3) -> ORD | AD13: =RIGHT(SalesData[[#This Row],[Order_ID]],4) -> 0935 | AE13: =_xlfn.CONCAT(SalesData[[#This Row],[Clean_Customer_Name]],"-",SalesData[[#This Row],[Region]]) -> Vikas Yadav-West | AF13: =MID(SalesData[[#This Row],[Order_ID]],4,4) -> 0935 | AG13: =_xlfn.SINGLE(_xlfn.XLOOKUP(SalesData[[#This Row],[Product]],Product_Master!A:A,Product_Master!B:B,"Not Found")) -> #NAME? | AH13: =VLOOKUP(SalesData[[#This Row],[Product]],Product_Master!$A$1:$B$21,2,FALSE) -> Anjali | AJ13: Total sales from N & Elec | AK13: =SUMIFS(SalesData[Sales],SalesData[Region],"South",SalesData[Category],"Electronics") -> 3176605.2
A14: ORD0133 | B14: 45448 | C14: C011 | D14: Vikas Yadav | E14: P009 | F14: Sofa | G14: Furniture | H14: Seating | I14: South | J14: Telangana | K14: 118525.4 | L14: 58459.32 | M14: 4 | N14: 0 | O14: Net Banking | P14: Delivered | Q14: =TRIM(SalesData[[#This Row],[Customer_Name]]) -> Vikas Yadav | R14: =SalesData[[#This Row],[Sales]]-SalesData[[#This Row],[Cost]] -> 60066.08 | S14: =IFERROR(SalesData[[#This Row],[Profit]]/SalesData[[#This Row],[Sales]],0) -> 0.50677813 | T14: =YEAR(SalesData[[#This Row],[Order_Date]]) -> 2024 | U14: =TEXT(SalesData[[#This Row],[Order_Date]],"mmm") -> Jun | V14: ="Q"&ROUNDUP(MONTH(SalesData[[#This Row],[Order_Date]])/3,0) -> Q2 | W14: =IF(SalesData[[#This Row],[Sales]]>=50000,"High",IF(AND(SalesData[[#This Row],[Sales]]>= 20000, SalesData[[#This Row],[Sales]]< 50000),"Medium","Low")) -> High | X14: =IF(SalesData[[#This Row],[Profit]]>0,"Profit","Loss") -> Profit | Y14: =IF(AND(SalesData[[#This Row],[Sales]]>= 50000, SalesData[[#This Row],[Quantity]]>=2),"Yes","No") -> Yes | Z14: =UPPER(SalesData[[#This Row],[Customer_Name]]) -> VIKAS YADAV | AA14: =LOWER(SalesData[[#This Row],[Customer_Name]]) -> vikas yadav | AB14: =LEN(SalesData[[#This Row],[Customer_Name]]) -> 11 | AC14: =LEFT(SalesData[[#This Row],[Order_ID]],3) -> ORD | AD14: =RIGHT(SalesData[[#This Row],[Order_ID]],4) -> 0133 | AE14: =_xlfn.CONCAT(SalesData[[#This Row],[Clean_Customer_Name]],"-",SalesData[[#This Row],[Region]]) -> Vikas Yadav-South | AF14: =MID(SalesData[[#This Row],[Order_ID]],4,4) -> 0133 | AG14: =_xlfn.SINGLE(_xlfn.XLOOKUP(SalesData[[#This Row],[Product]],Product_Master!A:A,Product_Master!B:B,"Not Found")) -> #NAME? | AH14: =VLOOKUP(SalesData[[#This Row],[Product]],Product_Master!$A$1:$B$21,2,FALSE) -> Arjun
A15: ORD0667 | B15: 45392 | C15: C011 | D15: Vikas Yadav | E15: P009 | F15: Sofa | G15: Furniture | H15: Seating | I15: South | J15: Tamil Nadu | K15: 66768.2 | L15: 49481.7 | M15: 3 | N15: 0.05 | O15: Cash on Delivery | P15: Delivered | Q15: =TRIM(SalesData[[#This Row],[Customer_Name]]) -> Vikas Yadav | R15: =SalesData[[#This Row],[Sales]]-SalesData[[#This Row],[Cost]] -> 17286.5 | S15: =IFERROR(SalesData[[#This Row],[Profit]]/SalesData[[#This Row],[Sales]],0) -> 0.25890319 | T15: =YEAR(SalesData[[#This Row],[Order_Date]]) -> 2024 | U15: =TEXT(SalesData[[#This Row],[Order_Date]],"mmm") -> Apr | V15: ="Q"&ROUNDUP(MONTH(SalesData[[#This Row],[Order_Date]])/3,0) -> Q2 | W15: =IF(SalesData[[#This Row],[Sales]]>=50000,"High",IF(AND(SalesData[[#This Row],[Sales]]>= 20000, SalesData[[#This Row],[Sales]]< 50000),"Medium","Low")) -> High | X15: =IF(SalesData[[#This Row],[Profit]]>0,"Profit","Loss") -> Profit | Y15: =IF(AND(SalesData[[#This Row],[Sales]]>= 50000, SalesData[[#This Row],[Quantity]]>=2),"Yes","No") -> Yes | Z15: =UPPER(SalesData[[#This Row],[Customer_Name]]) -> VIKAS YADAV | AA15: =LOWER(SalesData[[#This Row],[Customer_Name]]) -> vikas yadav | AB15: =LEN(SalesData[[#This Row],[Customer_Name]]) -> 11 | AC15: =LEFT(SalesData[[#This Row],[Order_ID]],3) -> ORD | AD15: =RIGHT(SalesData[[#This Row],[Order_ID]],4) -> 0667 | AE15: =_xlfn.CONCAT(SalesData[[#This Row],[Clean_Customer_Name]],"-",SalesData[[#This Row],[Region]]) -> Vikas Yadav-South | AF15: =MID(SalesData[[#This Row],[Order_ID]],4,4) -> 0667 | AG15: =_xlfn.SINGLE(_xlfn.XLOOKUP(SalesData[[#This Row],[Product]],Product_Master!A:A,Product_Master!B:B,"Not Found")) -> #NAME? | AH15: =VLOOKUP(SalesData[[#This Row],[Product]],Product_Master!$A$1:$B$21,2,FALSE) -> Arjun | AJ15: Average Sales | AK15: =AVERAGEIF(SalesData[Category],"furniture",SalesData[Sales]) -> 44496.553
A16: ORD0306 | B16: 45878 | C16: C011 | D16: Vikas Yadav | E16: P010 | F16: Bed | G16: Furniture | H16: Bedroom | I16: South | J16: Tamil Nadu | K16: 88011.48 | L16: 58885.89 | M16: 3 | N16: 0 | O16: Credit Card | P16: Cancelled | Q16: =TRIM(SalesData[[#This Row],[Customer_Name]]) -> Vikas Yadav | R16: =SalesData[[#This Row],[Sales]]-SalesData[[#This Row],[Cost]] -> 29125.59 | S16: =IFERROR(SalesData[[#This Row],[Profit]]/SalesData[[#This Row],[Sales]],0) -> 0.33092944 | T16: =YEAR(SalesData[[#This Row],[Order_Date]]) -> 2025 | U16: =TEXT(SalesData[[#This Row],[Order_Date]],"mmm") -> Aug | V16: ="Q"&ROUNDUP(MONTH(SalesData[[#This Row],[Order_Date]])/3,0) -> Q3 | W16: =IF(SalesData[[#This Row],[Sales]]>=50000,"High",IF(AND(SalesData[[#This Row],[Sales]]>= 20000, SalesData[[#This Row],[Sales]]< 50000),"Medium","Low")) -> High | X16: =IF(SalesData[[#This Row],[Profit]]>0,"Profit","Loss") -> Profit | Y16: =IF(AND(SalesData[[#This Row],[Sales]]>= 50000, SalesData[[#This Row],[Quantity]]>=2),"Yes","No") -> Yes | Z16: =UPPER(SalesData[[#This Row],[Customer_Name]]) -> VIKAS YADAV | AA16: =LOWER(SalesData[[#This Row],[Customer_Name]]) -> vikas yadav | AB16: =LEN(SalesData[[#This Row],[Customer_Name]]) -> 11 | AC16: =LEFT(SalesData[[#This Row],[Order_ID]],3) -> ORD | AD16: =RIGHT(SalesData[[#This Row],[Order_ID]],4) -> 0306 | AE16: =_xlfn.CONCAT(SalesData[[#This Row],[Clean_Customer_Name]],"-",SalesData[[#This Row],[Region]]) -> Vikas Yadav-South | AF16: =MID(SalesData[[#This Row],[Order_ID]],4,4) -> 0306 | AG16: =_xlfn.SINGLE(_xlfn.XLOOKUP(SalesData[[#This Row],[Product]],Product_Master!A:A,Product_Master!B:B,"Not Found")) -> #NAME? | AH16: =VLOOKUP(SalesData[[#This Row],[Product]],Product_Master!$A$1:$B$21,2,FALSE) -> Sneha
A17: ORD0679 | B17: 45348 | C17: C011 | D17: Vikas Yadav | E17: P010 | F17: Bed | G17: Furniture | H17: Bedroom | I17: West | J17: Maharashtra | K17: 31845.26 | L17: 17515.28 | M17: 1 | N17: 0.1 | O17: UPI | P17: Returned | Q17: =TRIM(SalesData[[#This Row],[Customer_Name]]) -> Vikas Yadav | R17: =SalesData[[#This Row],[Sales]]-SalesData[[#This Row],[Cost]] -> 14329.98 | S17: =IFERROR(SalesData[[#This Row],[Profit]]/SalesData[[#This Row],[Sales]],0) -> 0.44998785 | T17: =YEAR(SalesData[[#This Row],[Order_Date]]) -> 2024 | U17: =TEXT(SalesData[[#This Row],[Order_Date]],"mmm") -> Feb | V17: ="Q"&ROUNDUP(MONTH(SalesData[[#This Row],[Order_Date]])/3,0) -> Q1 | W17: =IF(SalesData[[#This Row],[Sales]]>=50000,"High",IF(AND(SalesData[[#This Row],[Sales]]>= 20000, SalesData[[#This Row],[Sales]]< 50000),"Medium","Low")) -> Medium | X17: =IF(SalesData[[#This Row],[Profit]]>0,"Profit","Loss") -> Profit | Y17: =IF(AND(SalesData[[#This Row],[Sales]]>= 50000, SalesData[[#This Row],[Quantity]]>=2),"Yes","No") -> No | Z17: =UPPER(SalesData[[#This Row],[Customer_Name]]) -> VIKAS YADAV | AA17: =LOWER(SalesData[[#This Row],[Customer_Name]]) -> vikas yadav | AB17: =LEN(SalesData[[#This Row],[Customer_Name]]) -> 11 | AC17: =LEFT(SalesData[[#This Row],[Order_ID]],3) -> ORD | AD17: =RIGHT(SalesData[[#This Row],[Order_ID]],4) -> 0679 | AE17: =_xlfn.CONCAT(SalesData[[#This Row],[Clean_Customer_Name]],"-",SalesData[[#This Row],[Region]]) -> Vikas Yadav-West | AF17: =MID(SalesData[[#This Row],[Order_ID]],4,4) -> 0679 | AG17: =_xlfn.SINGLE(_xlfn.XLOOKUP(SalesData[[#This Row],[Product]],Product_Master!A:A,Product_Master!B:B,"Not Found")) -> #NAME? | AH17: =VLOOKUP(SalesData[[#This Row],[Product]],Product_Master!$A$1:$B$21,2,FALSE) -> Sneha | AJ17: Average Sales by region | AK17: =AVERAGEIFS(SalesData[Sales],SalesData[Region],"West",SalesData[Category],"Electronics") -> 55883.702
A18: ORD0714 | B18: 45807 | C18: C011 | D18: Vikas Yadav | E18: P012 | F18: Jacket | G18: Fashion | H18: Clothing | I18: South | J18: Tamil Nadu | K18: 4311.36 | L18: 3439.56 | M18: 4 | N18: 0.1 | O18: Net Banking | P18: Returned | Q18: =TRIM(SalesData[[#This Row],[Customer_Name]]) -> Vikas Yadav | R18: =SalesData[[#This Row],[Sales]]-SalesData[[#This Row],[Cost]] -> 871.8 | S18: =IFERROR(SalesData[[#This Row],[Profit]]/SalesData[[#This Row],[Sales]],0) -> 0.20220998 | T18: =YEAR(SalesData[[#This Row],[Order_Date]]) -> 2025 | U18: =TEXT(SalesData[[#This Row],[Order_Date]],"mmm") -> May | V18: ="Q"&ROUNDUP(MONTH(SalesData[[#This Row],[Order_Date]])/3,0) -> Q2 | W18: =IF(SalesData[[#This Row],[Sales]]>=50000,"High",IF(AND(SalesData[[#This Row],[Sales]]>= 20000, SalesData[[#This Row],[Sales]]< 50000),"Medium","Low")) -> Low | X18: =IF(SalesData[[#This Row],[Profit]]>0,"Profit","Loss") -> Profit | Y18: =IF(AND(SalesData[[#This Row],[Sales]]>= 50000, SalesData[[#This Row],[Quantity]]>=2),"Yes","No") -> No | Z18: =UPPER(SalesData[[#This Row],[Customer_Name]]) -> VIKAS YADAV | AA18: =LOWER(SalesData[[#This Row],[Customer_Name]]) -> vikas yadav | AB18: =LEN(SalesData[[#This Row],[Customer_Name]]) -> 11 | AC18: =LEFT(SalesData[[#This Row],[Order_ID]],3) -> ORD | AD18: =RIGHT(SalesData[[#This Row],[Order_ID]],4) -> 0714 | AE18: =_xlfn.CONCAT(SalesData[[#This Row],[Clean_Customer_Name]],"-",SalesData[[#This Row],[Region]]) -> Vikas Yadav-South | AF18: =MID(SalesData[[#This Row],[Order_ID]],4,4) -> 0714 | AG18: =_xlfn.SINGLE(_xlfn.XLOOKUP(SalesData[[#This Row],[Product]],Product_Master!A:A,Product_Master!B:B,"Not Found")) -> #NAME? | AH18: =VLOOKUP(SalesData[[#This Row],[Product]],Product_Master!$A$1:$B$21,2,FALSE) -> Pooja
A19: ORD0586 | B19: 45452 | C19: C011 | D19: Vikas Yadav | E19: P016 | F19: Mixer Grinder | G19: Home Appliances | H19: Kitchen | I19: West | J19: Maharashtra | K19: 2917.86 | L19: 1744.84 | M19: 1 | N19: 0.1 | O19: Credit Card | P19: Shipped | Q19: =TRIM(SalesData[[#This Row],[Customer_Name]]) -> Vikas Yadav | R19: =SalesData[[#This Row],[Sales]]-SalesData[[#This Row],[Cost]] -> 1173.02 | S19: =IFERROR(SalesData[[#This Row],[Profit]]/SalesData[[#This Row],[Sales]],0) -> 0.4020138 | T19: =YEAR(SalesData[[#This Row],[Order_Date]]) -> 2024 | U19: =TEXT(SalesData[[#This Row],[Order_Date]],"mmm") -> Jun | V19: ="Q"&ROUNDUP(MONTH(SalesData[[#This Row],[Order_Date]])/3,0) -> Q2 | W19: =IF(SalesData[[#This Row],[Sales]]>=50000,"High",IF(AND(SalesData[[#This Row],[Sales]]>= 20000, SalesData[[#This Row],[Sales]]< 50000),"Medium","Low")) -> Low | X19: =IF(SalesData[[#This Row],[Profit]]>0,"Profit","Loss") -> Profit | Y19: =IF(AND(SalesData[[#This Row],[Sales]]>= 50000, SalesData[[#This Row],[Quantity]]>=2),"Yes","No") -> No | Z19: =UPPER(SalesData[[#This Row],[Customer_Name]]) -> VIKAS YADAV | AA19: =LOWER(SalesData[[#This Row],[Customer_Name]]) -> vikas yadav | AB19: =LEN(SalesData[[#This Row],[Customer_Name]]) -> 11 | AC19: =LEFT(SalesData[[#This Row],[Order_ID]],3) -> ORD | AD19: =RIGHT(SalesData[[#This Row],[Order_ID]],4) -> 0586 | AE19: =_xlfn.CONCAT(SalesData[[#This Row],[Clean_Customer_Name]],"-",SalesData[[#This Row],[Region]]) -> Vikas Yadav-West | AF19: =MID(SalesData[[#This Row],[Order_ID]],4,4) -> 0586 | AG19: =_xlfn.SINGLE(_xlfn.XLOOKUP(SalesData[[#This Row],[Product]],Product_Master!A:A,Product_Master!B:B,"Not Found")) -> #NAME? | AH19: =VLOOKUP(SalesData[[#This Row],[Product]],Product_Master!$A$1:$B$21,2,FALSE) -> Rahul
A20: ORD0644 | B20: 45968 | C20: C011 | D20: Vikas Yadav | E20: P016 | F20: Mixer Grinder | G20: Home Appliances | H20: Kitchen | I20: East | J20: Odisha | K20: 3890.04 | L20: 1652.59 | M20: 1 | N20: 0.2 | O20: UPI | P20: Delivered | Q20: =TRIM(SalesData[[#This Row],[Customer_Name]]) -> Vikas Yadav | R20: =SalesData[[#This Row],[Sales]]-SalesData[[#This Row],[Cost]] -> 2237.45 | S20: =IFERROR(SalesData[[#This Row],[Profit]]/SalesData[[#This Row],[Sales]],0) -> 0.57517403 | T20: =YEAR(SalesData[[#This Row],[Order_Date]]) -> 2025 | U20: =TEXT(SalesData[[#This Row],[Order_Date]],"mmm") -> Nov | V20: ="Q"&ROUNDUP(MONTH(SalesData[[#This Row],[Order_Date]])/3,0) -> Q4 | W20: =IF(SalesData[[#This Row],[Sales]]>=50000,"High",IF(AND(SalesData[[#This Row],[Sales]]>= 20000, SalesData[[#This Row],[Sales]]< 50000),"Medium","Low")) -> Low | X20: =IF(SalesData[[#This Row],[Profit]]>0,"Profit","Loss") -> Profit | Y20: =IF(AND(SalesData[[#This Row],[Sales]]>= 50000, SalesData[[#This Row],[Quantity]]>=2),"Yes","No") -> No | Z20: =UPPER(SalesData[[#This Row],[Customer_Name]]) -> VIKAS YADAV | AA20: =LOWER(SalesData[[#This Row],[Customer_Name]]) -> vikas yadav | AB20: =LEN(SalesData[[#This Row],[Customer_Name]]) -> 11 | AC20: =LEFT(SalesData[[#This Row],[Order_ID]],3) -> ORD | AD20: =RIGHT(SalesData[[#This Row],[Order_ID]],4) -> 0644 | AE20: =_xlfn.CONCAT(SalesData[[#This Row],[Clean_Customer_Name]],"-",SalesData[[#This Row],[Region]]) -> Vikas Yadav-East | AF20: =MID(SalesData[[#This Row],[Order_ID]],4,4) -> 0644 | AG20: =_xlfn.SINGLE(_xlfn.XLOOKUP(SalesData[[#This Row],[Product]],Product_Master!A:A,Product_Master!B:B,"Not Found")) -> #NAME? | AH20: =VLOOKUP(SalesData[[#This Row],[Product]],Product_Master!$A$1:$B$21,2,FALSE) -> Rahul
A21: ORD0861 | B21: 45489 | C21: C011 | D21: Vikas Yadav | E21: P017 | F21: Microwave | G21: Home Appliances | H21: Kitchen | I21: East | J21: West Bengal | K21: 19856.62 | L21: 17835.51 | M21: 3 | N21: 0.15 | O21: Net Banking | P21: Delivered | Q21: =TRIM(SalesData[[#This Row],[Customer_Name]]) -> Vikas Yadav | R21: =SalesData[[#This Row],[Sales]]-SalesData[[#This Row],[Cost]] -> 2021.11 | S21: =IFERROR(SalesData[[#This Row],[Profit]]/SalesData[[#This Row],[Sales]],0) -> 0.1017852 | T21: =YEAR(SalesData[[#This Row],[Order_Date]]) -> 2024 | U21: =TEXT(SalesData[[#This Row],[Order_Date]],"mmm") -> Jul | V21: ="Q"&ROUNDUP(MONTH(SalesData[[#This Row],[Order_Date]])/3,0) -> Q3 | W21: =IF(SalesData[[#This Row],[Sales]]>=50000,"High",IF(AND(SalesData[[#This Row],[Sales]]>= 20000, SalesData[[#This Row],[Sales]]< 50000),"Medium","Low")) -> Low | X21: =IF(SalesData[[#This Row],[Profit]]>0,"Profit","Loss") -> Profit | Y21: =IF(AND(SalesData[[#This Row],[Sales]]>= 50000, SalesData[[#This Row],[Quantity]]>=2),"Yes","No") -> No | Z21: =UPPER(SalesData[[#This Row],[Customer_Name]]) -> VIKAS YADAV | AA21: =LOWER(SalesData[[#This Row],[Customer_Name]]) -> vikas yadav | AB21: =LEN(SalesData[[#This Row],[Customer_Name]]) -> 11 | AC21: =LEFT(SalesData[[#This Row],[Order_ID]],3) -> ORD | AD21: =RIGHT(SalesData[[#This Row],[Order_ID]],4) -> 0861 | AE21: =_xlfn.CONCAT(SalesData[[#This Row],[Clean_Customer_Name]],"-",SalesData[[#This Row],[Region]]) -> Vikas Yadav-East | AF21: =MID(SalesData[[#This Row],[Order_ID]],4,4) -> 0861 | AG21: =_xlfn.SINGLE(_xlfn.XLOOKUP(SalesData[[#This Row],[Product]],Product_Master!A:A,Product_Master!B:B,"Not Found")) -> #NAME? | AH21: =VLOOKUP(SalesData[[#This Row],[Product]],Product_Master!$A$1:$B$21,2,FALSE) -> Priya
A22: ORD0563 | B22: 45672 | C22: C011 | D22: Vikas Yadav | E22: P018 | F22: Air Cooler | G22: Home Appliances | H22: Cooling | I22: South | J22: Telangana | K22: 32778.79 | L22: 23162.4 | M22: 4 | N22: 0.1 | O22: Cash on Delivery | P22: Delivered | Q22: =TRIM(SalesData[[#This Row],[Customer_Name]]) -> Vikas Yadav | R22: =SalesData[[#This Row],[Sales]]-SalesData[[#This Row],[Cost]] -> 9616.39 | S22: =IFERROR(SalesData[[#This Row],[Profit]]/SalesData[[#This Row],[Sales]],0) -> 0.29337233 | T22: =YEAR(SalesData[[#This Row],[Order_Date]]) -> 2025 | U22: =TEXT(SalesData[[#This Row],[Order_Date]],"mmm") -> Jan | V22: ="Q"&ROUNDUP(MONTH(SalesData[[#This Row],[Order_Date]])/3,0) -> Q1 | W22: =IF(SalesData[[#This Row],[Sales]]>=50000,"High",IF(AND(SalesData[[#This Row],[Sales]]>= 20000, SalesData[[#This Row],[Sales]]< 50000),"Medium","Low")) -> Medium | X22: =IF(SalesData[[#This Row],[Profit]]>0,"Profit","Loss") -> Profit | Y22: =IF(AND(SalesData[[#This Row],[Sales]]>= 50000, SalesData[[#This Row],[Quantity]]>=2),"Yes","No") -> No | Z22: =UPPER(SalesData[[#This Row],[Customer_Name]]) -> VIKAS YADAV | AA22: =LOWER(SalesData[[#This Row],[Customer_Name]]) -> vikas yadav | AB22: =LEN(SalesData[[#This Row],[Customer_Name]]) -> 11 | AC22: =LEFT(SalesData[[#This Row],[Order_ID]],3) -> ORD | AD22: =RIGHT(SalesData[[#This Row],[Order_ID]],4) -> 0563 | AE22: =_xlfn.CONCAT(SalesData[[#This Row],[Clean_Customer_Name]],"-",SalesData[[#This Row],[Region]]) -> Vikas Yadav-South | AF22: =MID(SalesData[[#This Row],[Order_ID]],4,4) -> 0563 | AG22: =_xlfn.SINGLE(_xlfn.XLOOKUP(SalesData[[#This Row],[Product]],Product_Master!A:A,Product_Master!B:B,"Not Found")) -> #NAME? | AH22: =VLOOKUP(SalesData[[#This Row],[Product]],Product_Master!$A$1:$B$21,2,FALSE) -> Amit
A23: ORD0104 | B23: 45699 | C23: C011 | D23: Vikas Yadav | E23: P020 | F23: Electric Kettle | G23: Home Appliances | H23: Kitchen | I23: East | J23: Bihar | K23: 1298.25 | L23: 535.18 | M23: 1 | N23: 0.2 | O23: Net Banking | P23: Processing | Q23: =TRIM(SalesData[[#This Row],[Customer_Name]]) -> Vikas Yadav | R23: =SalesData[[#This Row],[Sales]]-SalesData[[#This Row],[Cost]] -> 763.07 | S23: =IFERROR(SalesData[[#This Row],[Profit]]/SalesData[[#This Row],[Sales]],0) -> 0.58776815 | T23: =YEAR(SalesData[[#This Row],[Order_Date]]) -> 2025 | U23: =TEXT(SalesData[[#This Row],[Order_Date]],"mmm") -> Feb | V23: ="Q"&ROUNDUP(MONTH(SalesData[[#This Row],[Order_Date]])/3,0) -> Q1 | W23: =IF(SalesData[[#This Row],[Sales]]>=50000,"High",IF(AND(SalesData[[#This Row],[Sales]]>= 20000, SalesData[[#This Row],[Sales]]< 50000),"Medium","Low")) -> Low | X23: =IF(SalesData[[#This Row],[Profit]]>0,"Profit","Loss") -> Profit | Y23: =IF(AND(SalesData[[#This Row],[Sales]]>= 50000, SalesData[[#This Row],[Quantity]]>=2),"Yes","No") -> No | Z23: =UPPER(SalesData[[#This Row],[Customer_Name]]) -> VIKAS YADAV | AA23: =LOWER(SalesData[[#This Row],[Customer_Name]]) -> vikas yadav | AB23: =LEN(SalesData[[#This Row],[Customer_Name]]) -> 11 | AC23: =LEFT(SalesData[[#This Row],[Order_ID]],3) -> ORD | AD23: =RIGHT(SalesData[[#This Row],[Order_ID]],4) -> 0104 | AE23: =_xlfn.CONCAT(SalesData[[#This Row],[Clean_Customer_Name]],"-",SalesData[[#This Row],[Region]]) -> Vikas Yadav-East | AF23: =MID(SalesData[[#This Row],[Order_ID]],4,4) -> 0104 | AG23: =_xlfn.SINGLE(_xlfn.XLOOKUP(SalesData[[#This Row],[Product]],Product_Master!A:A,Product_Master!B:B,"Not Found")) -> #NAME? | AH23: =VLOOKUP(SalesData[[#This Row],[Product]],Product_Master!$A$1:$B$21,2,FALSE) -> Simran
A24: ORD0130 | B24: 45359 | C24: C011 | D24: Vikas Yadav | E24: P020 | F24: Electric Kettle | G24: Home Appliances | H24: Kitchen | I24: North | J24: Punjab | K24: 2175.5 | L24: 955 | M24: 2 | N24: 0.2 | O24: Debit Card | P24: Cancelled | Q24: =TRIM(SalesData[[#This Row],[Customer_Name]]) -> Vikas Yadav | R24: =SalesData[[#This Row],[Sales]]-SalesData[[#This Row],[Cost]] -> 1220.5 | S24: =IFERROR(SalesData[[#This Row],[Profit]]/SalesData[[#This Row],[Sales]],0) -> 0.56102046 | T24: =YEAR(SalesData[[#This Row],[Order_Date]]) -> 2024 | U24: =TEXT(SalesData[[#This Row],[Order_Date]],"mmm") -> Mar | V24: ="Q"&ROUNDUP(MONTH(SalesData[[#This Row],[Order_Date]])/3,0) -> Q1 | W24: =IF(SalesData[[#This Row],[Sales]]>=50000,"High",IF(AND(SalesData[[#This Row],[Sales]]>= 20000, SalesData[[#This Row],[Sales]]< 50000),"Medium","Low")) -> Low | X24: =IF(SalesData[[#This Row],[Profit]]>0,"Profit","Loss") -> Profit | Y24: =IF(AND(SalesData[[#This Row],[Sales]]>= 50000, SalesData[[#This Row],[Quantity]]>=2),"Yes","No") -> No | Z24: =UPPER(SalesData[[#This Row],[Customer_Name]]) -> VIKAS YADAV | AA24: =LOWER(SalesData[[#This Row],[Customer_Name]]) -> vikas yadav | AB24: =LEN(SalesData[[#This Row],[Customer_Name]]) -> 11 | AC24: =LEFT(SalesData[[#This Row],[Order_ID]],3) -> ORD | AD24: =RIGHT(SalesData[[#This Row],[Order_ID]],4) -> 0130 | AE24: =_xlfn.CONCAT(SalesData[[#This Row],[Clean_Customer_Name]],"-",SalesData[[#This Row],[Region]]) -> Vikas Yadav-North | AF24: =MID(SalesData[[#This Row],[Order_ID]],4,4) -> 0130 | AG24: =_xlfn.SINGLE(_xlfn.XLOOKUP(SalesData[[#This Row],[Product]],Product_Master!A:A,Product_Master!B:B,"Not Found")) -> #NAME? | AH24: =VLOOKUP(SalesData[[#This Row],[Product]],Product_Master!$A$1:$B$21,2,FALSE) -> Simran
A25: ORD0155 | B25: 45805 | C25: C011 | D25: Vikas Yadav | E25: P020 | F25: Electric Kettle | G25: Home Appliances | H25: Kitchen | I25: West | J25: Gujarat | K25: 2053.13 | L25: 1091.54 | M25: 2 | N25: 0.1 | O25: UPI | P25: Delivered | Q25: =TRIM(SalesData[[#This Row],[Customer_Name]]) -> Vikas Yadav | R25: =SalesData[[#This Row],[Sales]]-SalesData[[#This Row],[Cost]] -> 961.59 | S25: =IFERROR(SalesData[[#This Row],[Profit]]/SalesData[[#This Row],[Sales]],0) -> 0.4683532 | T25: =YEAR(SalesData[[#This Row],[Order_Date]]) -> 2025 | U25: =TEXT(SalesData[[#This Row],[Order_Date]],"mmm") -> May | V25: ="Q"&ROUNDUP(MONTH(SalesData[[#This Row],[Order_Date]])/3,0) -> Q2 | W25: =IF(SalesData[[#This Row],[Sales]]>=50000,"High",IF(AND(SalesData[[#This Row],[Sales]]>= 20000, SalesData[[#This Row],[Sales]]< 50000),"Medium","Low")) -> Low | X25: =IF(SalesData[[#This Row],[Profit]]>0,"Profit","Loss") -> Profit | Y25: =IF(AND(SalesData[[#This Row],[Sales]]>= 50000, SalesData[[#This Row],[Quantity]]>=2),"Yes","No") -> No | Z25: =UPPER(SalesData[[#This Row],[Customer_Name]]) -> VIKAS YADAV | AA25: =LOWER(SalesData[[#This Row],[Customer_Name]]) -> vikas yadav | AB25: =LEN(SalesData[[#This Row],[Customer_Name]]) -> 11 | AC25: =LEFT(SalesData[[#This Row],[Order_ID]],3) -> ORD | AD25: =RIGHT(SalesData[[#This Row],[Order_ID]],4) -> 0155 | AE25: =_xlfn.CONCAT(SalesData[[#This Row],[Clean_Customer_Name]],"-",SalesData[[#This Row],[Region]]) -> Vikas Yadav-West | AF25: =MID(SalesData[[#This Row],[Order_ID]],4,4) -> 0155 | AG25: =_xlfn.SINGLE(_xlfn.XLOOKUP(SalesData[[#This Row],[Product]],Product_Master!A:A,Product_Master!B:B,"Not Found")) -> #NAME? | AH25: =VLOOKUP(SalesData[[#This Row],[Product]],Product_Master!$A$1:$B$21,2,FALSE) -> Simran
A26: ORD0361 | B26: 45425 | C26: C011 | D26: Vikas Yadav | E26: P020 | F26: Electric Kettle | G26: Home Appliances | H26: Kitchen | I26: South | J26: Karnataka | K26: 4596.86 | L26: 1565.07 | M26: 3 | N26: 0.1 | O26: UPI | P26: Delivered | Q26: =TRIM(SalesData[[#This Row],[Customer_Name]]) -> Vikas Yadav | R26: =SalesData[[#This Row],[Sales]]-SalesData[[#This Row],[Cost]] -> 3031.79 | S26: =IFERROR(SalesData[[#This Row],[Profit]]/SalesData[[#This Row],[Sales]],0) -> 0.65953499 | T26: =YEAR(SalesData[[#This Row],[Order_Date]]) -> 2024 | U26: =TEXT(SalesData[[#This Row],[Order_Date]],"mmm") -> May | V26: ="Q"&ROUNDUP(MONTH(SalesData[[#This Row],[Order_Date]])/3,0) -> Q2 | W26: =IF(SalesData[[#This Row],[Sales]]>=50000,"High",IF(AND(SalesData[[#This Row],[Sales]]>= 20000, SalesData[[#This Row],[Sales]]< 50000),"Medium","Low")) -> Low | X26: =IF(SalesData[[#This Row],[Profit]]>0,"Profit","Loss") -> Profit | Y26: =IF(AND(SalesData[[#This Row],[Sales]]>= 50000, SalesData[[#This Row],[Quantity]]>=2),"Yes","No") -> No | Z26: =UPPER(SalesData[[#This Row],[Customer_Name]]) -> VIKAS YADAV | AA26: =LOWER(SalesData[[#This Row],[Customer_Name]]) -> vikas yadav | AB26: =LEN(SalesData[[#This Row],[Customer_Name]]) -> 11 | AC26: =LEFT(SalesData[[#This Row],[Order_ID]],3) -> ORD | AD26: =RIGHT(SalesData[[#This Row],[Order_ID]],4) -> 0361 | AE26: =_xlfn.CONCAT(SalesData[[#This Row],[Clean_Customer_Name]],"-",SalesData[[#This Row],[Region]]) -> Vikas Yadav-South | AF26: =MID(SalesData[[#This Row],[Order_ID]],4,4) -> 0361 | AG26: =_xlfn.SINGLE(_xlfn.XLOOKUP(SalesData[[#This Row],[Product]],Product_Master!A:A,Product_Master!B:B,"Not Found")) -> #NAME? | AH26: =VLOOKUP(SalesData[[#This Row],[Product]],Product_Master!$A$1:$B$21,2,FALSE) -> Simran
A27: ORD0785 | B27: 45357 | C27: C011 | D27: Vikas Yadav | E27: P020 | F27: Electric Kettle | G27: Home Appliances | H27: Kitchen | I27: South | J27: Tamil Nadu | K27: 5624.04 | L27: 2158.72 | M27: 4 | N27: 0 | O27: Net Banking | P27: Delivered | Q27: =TRIM(SalesData[[#This Row],[Customer_Name]]) -> Vikas Yadav | R27: =SalesData[[#This Row],[Sales]]-SalesData[[#This Row],[Cost]] -> 3465.32 | S27: =IFERROR(SalesData[[#This Row],[Profit]]/SalesData[[#This Row],[Sales]],0) -> 0.61616205 | T27: =YEAR(SalesData[[#This Row],[Order_Date]]) -> 2024 | U27: =TEXT(SalesData[[#This Row],[Order_Date]],"mmm") -> Mar | V27: ="Q"&ROUNDUP(MONTH(SalesData[[#This Row],[Order_Date]])/3,0) -> Q1 | W27: =IF(SalesData[[#This Row],[Sales]]>=50000,"High",IF(AND(SalesData[[#This Row],[Sales]]>= 20000, SalesData[[#This Row],[Sales]]< 50000),"Medium","Low")) -> Low | X27: =IF(SalesData[[#This Row],[Profit]]>0,"Profit","Loss") -> Profit | Y27: =IF(AND(SalesData[[#This Row],[Sales]]>= 50000, SalesData[[#This Row],[Quantity]]>=2),"Yes","No") -> No | Z27: =UPPER(SalesData[[#This Row],[Customer_Name]]) -> VIKAS YADAV | AA27: =LOWER(SalesData[[#This Row],[Customer_Name]]) -> vikas yadav | AB27: =LEN(SalesData[[#This Row],[Customer_Name]]) -> 11 | AC27: =LEFT(SalesData[[#This Row],[Order_ID]],3) -> ORD | AD27: =RIGHT(SalesData[[#This Row],[Order_ID]],4) -> 0785 | AE27: =_xlfn.CONCAT(SalesData[[#This Row],[Clean_Customer_Name]],"-",SalesData[[#This Row],[Region]]) -> Vikas Yadav-South | AF27: =MID(SalesData[[#This Row],[Order_ID]],4,4) -> 0785 | AG27: =_xlfn.SINGLE(_xlfn.XLOOKUP(SalesData[[#This Row],[Product]],Product_Master!A:A,Product_Master!B:B,"Not Found")) -> #NAME? | AH27: =VLOOKUP(SalesData[[#This Row],[Product]],Product_Master!$A$1:$B$21,2,FALSE) -> Simran
A28: ORD0372 | B28: 45961 | C28: C023 | D28: Varun Kapoor | E28: P001 | F28: Laptop | G28: Electronics | H28: Computers | I28: West | J28: Maharashtra | K28: 117280.82 | L28: 98060.5 | M28: 2 | N28: 0 | O28: UPI | P28: Processing | Q28: =TRIM(SalesData[[#This Row],[Customer_Name]]) -> Varun Kapoor | R28: =SalesData[[#This Row],[Sales]]-SalesData[[#This Row],[Cost]] -> 19220.32 | S28: =IFERROR(SalesData[[#This Row],[Profit]]/SalesData[[#This Row],[Sales]],0) -> 0.16388289 | T28: =YEAR(SalesData[[#This Row],[Order_Date]]) -> 2025 | U28: =TEXT(SalesData[[#This Row],[Order_Date]],"mmm") -> Oct | V28: ="Q"&ROUNDUP(MONTH(SalesData[[#This Row],[Order_Date]])/3,0) -> Q4 | W28: =IF(SalesData[[#This Row],[Sales]]>=50000,"High",IF(AND(SalesData[[#This Row],[Sales]]>= 20000, SalesData[[#This Row],[Sales]]< 50000),"Medium","Low")) -> High | X28: =IF(SalesData[[#This Row],[Profit]]>0,"Profit","Loss") -> Profit | Y28: =IF(AND(SalesData[[#This Row],[Sales]]>= 50000, SalesData[[#This Row],[Quantity]]>=2),"Yes","No") -> Yes | Z28: =UPPER(SalesData[[#This Row],[Customer_Name]]) -> VARUN KAPOOR | AA28: =LOWER(SalesData[[#This Row],[Customer_Name]]) -> varun kapoor | AB28: =LEN(SalesData[[#This Row],[Customer_Name]]) -> 12 | AC28: =LEFT(SalesData[[#This Row],[Order_ID]],3) -> ORD | AD28: =RIGHT(SalesData[[#This Row],[Order_ID]],4) -> 0372 | AE28: =_xlfn.CONCAT(SalesData[[#This Row],[Clean_Customer_Name]],"-",SalesData[[#This Row],[Region]]) -> Varun Kapoor-West | AF28: =MID(SalesData[[#This Row],[Order_ID]],4,4) -> 0372 | AG28: =_xlfn.SINGLE(_xlfn.XLOOKUP(SalesData[[#This Row],[Product]],Product_Master!A:A,Product_Master!B:B,"Not Found")) -> #NAME? | AH28: =VLOOKUP(SalesData[[#This Row],[Product]],Product_Master!$A$1:$B$21,2,FALSE) -> Rahul
A29: ORD0998 | B29: 45626 | C29: C023 | D29: Varun Kapoor | E29: P001 | F29: Laptop | G29: Electronics | H29: Computers | I29: North | J29: Punjab | K29: 202453.31 | L29: 202226.24 | M29: 4 | N29: 0.1 | O29: Net Banking | P29: Delivered | Q29: =TRIM(SalesData[[#This Row],[Customer_Name]]) -> Varun Kapoor | R29: =SalesData[[#This Row],[Sales]]-SalesData[[#This Row],[Cost]] -> 227.07 | S29: =IFERROR(SalesData[[#This Row],[Profit]]/SalesData[[#This Row],[Sales]],0) -> 0.0011215919 | T29: =YEAR(SalesData[[#This Row],[Order_Date]]) -> 2024 | U29: =TEXT(SalesData[[#This Row],[Order_Date]],"mmm") -> Nov | V29: ="Q"&ROUNDUP(MONTH(SalesData[[#This Row],[Order_Date]])/3,0) -> Q4 | W29: =IF(SalesData[[#This Row],[Sales]]>=50000,"High",IF(AND(SalesData[[#This Row],[Sales]]>= 20000, SalesData[[#This Row],[Sales]]< 50000),"Medium","Low")) -> High | X29: =IF(SalesData[[#This Row],[Profit]]>0,"Profit","Loss") -> Profit | Y29: =IF(AND(SalesData[[#This Row],[Sales]]>= 50000, SalesData[[#This Row],[Quantity]]>=2),"Yes","No") -> Yes | Z29: =UPPER(SalesData[[#This Row],[Customer_Name]]) -> VARUN KAPOOR | AA29: =LOWER(SalesData[[#This Row],[Customer_Name]]) -> varun kapoor | AB29: =LEN(SalesData[[#This Row],[Customer_Name]]) -> 12 | AC29: =LEFT(SalesData[[#This Row],[Order_ID]],3) -> ORD | AD29: =RIGHT(SalesData[[#This Row],[Order_ID]],4) -> 0998 | AE29: =_xlfn.CONCAT(SalesData[[#This Row],[Clean_Customer_Name]],"-",SalesData[[#This Row],[Region]]) -> Varun Kapoor-North | AF29: =MID(SalesData[[#This Row],[Order_ID]],4,4) -> 0998 | AG29: =_xlfn.SINGLE(_xlfn.XLOOKUP(SalesData[[#This Row],[Product]],Product_Master!A:A,Product_Master!B:B,"Not Found")) -> #NAME? | AH29: =VLOOKUP(SalesData[[#This Row],[Product]],Product_Master!$A$1:$B$21,2,FALSE) -> Rahul
... A1001: ORD0598 | B1001: 45877 | C1001: C013 | D1001: Aditya Jain | E1001: P020 | F1001: Electric Kettle | G1001: Home Appliances | H1001: Kitchen | I1001: East | J1001: Bihar | K1001: 6848.35 | L1001: 2518.1 | M1001: 5 | N1001: 0 | O1001: Cash on Delivery | P1001: Delivered | Q1001: =TRIM(SalesData[[#This Row],[Customer_Name]]) -> Aditya Jain | R1001: =SalesData[[#This Row],[Sales]]-SalesData[[#This Row],[Cost]] -> 4330.25 | S1001: =IFERROR(SalesData[[#This Row],[Profit]]/SalesData[[#This Row],[Sales]],0) -> 0.63230559 | T1001: =YEAR(SalesData[[#This Row],[Order_Date]]) -> 2025 | U1001: =TEXT(SalesData[[#This Row],[Order_Date]],"mmm") -> Aug | V1001: ="Q"&ROUNDUP(MONTH(SalesData[[#This Row],[Order_Date]])/3,0) -> Q3 | W1001: =IF(SalesData[[#This Row],[Sales]]>=50000,"High",IF(AND(SalesData[[#This Row],[Sales]]>= 20000, SalesData[[#This Row],[Sales]]< 50000),"Medium","Low")) -> Low | X1001: =IF(SalesData[[#This Row],[Profit]]>0,"Profit","Loss") -> Profit | Y1001: =IF(AND(SalesData[[#This Row],[Sales]]>= 50000, SalesData[[#This Row],[Quantity]]>=2),"Yes","No") -> No | Z1001: =UPPER(SalesData[[#This Row],[Customer_Name]]) -> ADITYA JAIN | AA1001: =LOWER(SalesData[[#This Row],[Customer_Name]]) -> aditya jain | AB1001: =LEN(SalesData[[#This Row],[Customer_Name]]) -> 11 | AC1001: =LEFT(SalesData[[#This Row],[Order_ID]],3) -> ORD | AD1001: =RIGHT(SalesData[[#This Row],[Order_ID]],4) -> 0598 | AE1001: =_xlfn.CONCAT(SalesData[[#This Row],[Clean_Customer_Name]],"-",SalesData[[#This Row],[Region]]) -> Aditya Jain-East | AF1001: =MID(SalesData[[#This Row],[Order_ID]],4,4) -> 0598 | AG1001: =_xlfn.SINGLE(_xlfn.XLOOKUP(SalesData[[#This Row],[Product]],Product_Master!A:A,Product_Master!B:B,"Not Found")) -> #NAME? | AH1001: =VLOOKUP(SalesData[[#This Row],[Product]],Product_Master!$A$1:$B$21,2,FALSE) -> Simran

Sheet Pivot_Analysis
A1: Region | B1: Sum of Sales | D1: Categories | E1: Sum of Sales | G1: Product | H1: Sum of Sales | J1: Year wise Months | K1: Sum of Sales
A2: Central | B2: 5237039.4 | D2: Electronics | E2: 14670585 | G2: Air Cooler | H2: 1356481.7 | J2: 2024 | K2: 15456937
A3: East | B3: 6067721.1 | D3: Fashion | E3: 1409923.8 | G3: Backpack | H3: 309021.81 | J3: Jan | K3: 923718.02
A4: North | B4: 5874947 | D4: Furniture | E4: 10100718 | G4: Bed | H4: 3948297.9 | J4: Feb | K4: 1883708.6
A5: South | B5: 6974975.6 | D5: Home Appliances | E5: 4308884.8 | G5: Bookshelf | H5: 996851.05 | J5: Mar | K5: 743073.3
A6: West | B6: 6335428.4 | G6: Electric Kettle | H6: 179788.73 | J6: Apr | K6: 1302885.7
G7: Headphones | H7: 726025.01 | J7: May | K7: 1701487.5
G8: Jacket | H8: 241567.2 | J8: Jun | K8: 1560945.9
A9: Region | B9: Sum of Profit | D9: Categories | E9: Count of Order_ID | G9: Jeans | H9: 262071.15 | J9: Jul | K9: 916590.86
A10: Central | B10: 1724615.6 | D10: Electronics | E10: 266 | G10: Laptop | H10: 7037458.6 | J10: Aug | K10: 920956.45
A11: East | B11: 1695740.7 | D11: Fashion | E11: 264 | G11: Microwave | H11: 1530673.6 | J11: Sept | K11: 1025606.6
A12: North | B12: 1779101.1 | D12: Furniture | E12: 227 | G12: Mixer Grinder | H12: 554989.15 | J12: Oct | K12: 1394735.6
A13: South | B13: 1983635.8 | D13: Home Appliances | E13: 243 | G13: Mobile | H13: 4194370.1 | J13: Nov | K13: 1689430.4
A14: West | B14: 1923582.8 | G14: Monitor | H14: 1596495.5 | J14: Dec | K14: 1393797.6
G15: Office Chair | H15: 909098.25 | J15: 2025 | K15: 15033175
G16: Running Shoes | H16: 478971.88 | J16: Jan | K16: 1062300
G17: Smart Watch | H17: 1116236.1 | J17: Feb | K17: 1148589.2
G18: Sofa | H18: 2661005.5 | J18: Mar | K18: 1162416.5
G19: Study Table | H19: 1585464.9 | J19: Apr | K19: 1393344.3
G20: T-Shirt | H20: 118291.77 | J20: May | K20: 1215926.4
G21: Vacuum Cleaner | H21: 686951.64 | J21: Jun | K21: 806165.72
J22: Jul | K22: 1101054.5
J23: Aug | K23: 1398247.7
J24: Sept | K24: 1052692.6
J25: Oct | K25: 1733530.2
J26: Nov | K26: 1628962.8
J27: Dec | K27: 1329944.8

Sheet Dashboard
B3: Total Sales | D3: Total Profit | F3: Total Order | H3: Profit Margin
B4: =SUM(SalesData[Sales]) -> 30490111 | D4: =SUM(SalesData[Profit]) -> 9106676 | F4: =COUNTA(SalesData[Order_ID]) -> 1000 | H4: =SUM(SalesData[Profit])/SUM(SalesData[Sales]) -> 0.29867638

Sheet Product_Master
A1: Product | B1: Product_Manager
A2: Laptop | B2: Rahul
A3: Mobile | B3: Priya
A4: Headphones | B4: Amit
A5: Smart Watch | B5: Neha
A6: Monitor | B6: Simran
A7: Office Chair | B7: Karan
A8: Study Table | B8: Rohan
A9: Bookshelf | B9: Anjali
A10: Sofa | B10: Arjun
A11: Bed | B11: Sneha
A12: Running Shoes | B12: Vikas
... A21: Electric Kettle | B21: Simran

Sheet Project_Guide
A1: E-Commerce Sales Analysis – Excel Revision Project
A2: Dataset | B2: 1,000 transaction rows in Raw_Data
A3: Practice areas | B3: Data cleaning, IF/IFS, SUMIF/SUMIFS, COUNTIF/COUNTIFS, AVERAGEIF, XLOOKUP/VLOOKUP, INDEX-MATCH, date/text functions, PivotTables, charts, slicers, dashboard
A4: Suggested calculated columns | B4: Profit, Profit Margin %, Year, Month, Quarter, Sales Category
A5: First task | B5: Create a copy of Raw_Data named Cleaned_Data and begin your cleaning/analysis there.
